{"msg": "\u6210\u529f", "code": 0, "data": {"pagination": {"total_count": 44862, "limit": 20, "page": 59}, "recommends": [], "authors": [{"long_video_price": 21000, "is_star": true, "rank": 1, "follower": 1492331, "create_time": 1543602735, "total_favour_cnt": 15690826, "avg_play": 569068, "abandon_sign_result": 0, "cut_rate": 0.0, "appeal_id": 0, "city": "", "short_id": 350512586, "online_status": 1, "platform_source": 1, "id": "6629723261749952515", "recommend": false, "lowest_price": 2010, "price": 12000, "author_type": 1, "province": "\u6e56\u5317\u7701", "tags": "[\"\u4f53\u80b2\"]", "next_month_long_video_price": 21000, "next_month_price": 12000, "is_online": true, "has_phone": true, "core_user_id": 85259219370, "task_status": 1, "protocol_id": 2018006, "nick_name": "\u4ebf\u5143\u4ebf\u5143", "gender": 2, "aweme_tags": [], "order_cnt": 16, "rate": 1.05, "modify_time": 1558452882, "avatar_uri": "https://p3-dy.byteimg.com/aweme/1080x1080/1b4db00041d6952c8a848.jpeg", "price_info": [{"field": "price", "price": 12000, "video_type": 1, "desc": "1-20s\u89c6\u9891"}, {"field": "long_video_price", "price": 21000, "video_type": 2, "desc": "21-60s\u89c6\u9891"}], "category_id": 1, "unique_id": "yiyuan10"}, {"long_video_price": 85715, "is_star": true, "rank": 2, "follower": 2149991, "create_time": 1543602703, "total_favour_cnt": 23644050, "avg_play": 1253772, "abandon_sign_result": 0, "cut_rate": 0.0, "appeal_id": 0, "city": "", "short_id": 8782918, "online_status": 1, "platform_source": 1, "id": "6629723124734623747", "recommend": false, "lowest_price": 3984, "price": 65700, "author_type": 2, "province": null, "tags": "[]", "next_month_long_video_price": 85715, "next_month_price": 65700, "is_online": true, "has_phone": true, "core_user_id": 59118608713, "task_status": 1, "protocol_id": 2018008, "nick_name": "\u5c0f\u738b\u5b50\u672c\u4eba", "gender": 1, "aweme_tags": [], "order_cnt": 9, "rate": 1.05, "modify_time": 1558452866, "avatar_uri": "https://p3-dy.byteimg.com/aweme/1080x1080/1b5fa000026b0cdc41781.jpeg", "price_info": [{"field": "price", "price": 65700, "video_type": 1, "desc": "1-20s\u89c6\u9891"}, {"field": "long_video_price", "price": 85715, "video_type": 2, "desc": "21-60s\u89c6\u9891"}], "category_id": 5, "unique_id": 8782918}, {"long_video_price": 16000, "is_star": true, "rank": 3, "follower": 732052, "create_time": 1551329965, "total_favour_cnt": 11680415, "avg_play": 9146736, "abandon_sign_result": 0, "cut_rate": 0.0, "appeal_id": 0, "city": "", "short_id": 1813842424, "online_status": 1, "platform_source": 1, "id": "6662911468301713412", "recommend": false, "lowest_price": 1000, "price": 15000, "author_type": 1, "province": "\u6d59\u6c5f\u7701", "tags": "[\"\u65f6\u5c1a\",\"\u60c5\u611f\",\"\u751f\u6d3b\",\"\u65c5\u884c\",\"\u7f8e\u5986\"]", "next_month_long_video_price": 0, "next_month_price": 20000, "is_online": true, "has_phone": true, "core_user_id": 106211588923, "task_status": 1, "protocol_id": 2018006, "nick_name": "\u745e\u62c9 \u5fd8\u5e74\u604b", "gender": 1, "aweme_tags": [], "order_cnt": 6, "rate": 1.05, "modify_time": 1558453168, "avatar_uri": "https://p3-dy.byteimg.com/aweme/1080x1080/173300002b1591cf81cc4.jpeg", "price_info": [{"field": "price", "price": 15000, "video_type": 1, "desc": "1-20s\u89c6\u9891"}, {"field": "long_video_price", "price": 16000, "video_type": 2, "desc": "21-60s\u89c6\u9891"}], "category_id": 1, "unique_id": "WangNianLian"}, {"long_video_price": 30000, "is_star": true, "rank": 4, "follower": 2316070, "create_time": 1540521967, "total_favour_cnt": 25100525, "avg_play": 1331046, "abandon_sign_result": 0, "cut_rate": 0.0, "appeal_id": 0, "city": "", "short_id": 1217044060, "online_status": 1, "platform_source": 1, "id": "6616491468674564110", "recommend": false, "lowest_price": 3599, "price": 25000, "author_type": 1, "province": null, "tags": "[]", "next_month_long_video_price": 30000, "next_month_price": 25000, "is_online": true, "has_phone": true, "core_user_id": 72240612784, "task_status": 1, "protocol_id": 2018006, "nick_name": "\u9ec4\u80dc\u5174\uff08\u641e\u7b11\u5927\u5b59\u5b50\uff09", "gender": 1, "aweme_tags": [], "order_cnt": 1, "rate": 1.05, "modify_time": 1558451199, "avatar_uri": "https://p3-dy.byteimg.com/aweme/1080x1080/1cab20006d1d11cc6fa5a.jpeg", "price_info": [{"field": "price", "price": 25000, "video_type": 1, "desc": "1-20s\u89c6\u9891"}, {"field": "long_video_price", "price": 30000, "video_type": 2, "desc": "21-60s\u89c6\u9891"}], "category_id": 1, "unique_id": 1217044060}, {"long_video_price": 9000, "is_star": true, "rank": 5, "follower": 320711, "create_time": 1543587599, "total_favour_cnt": 4732468, "avg_play": 297316, "abandon_sign_result": 0, "cut_rate": 0.0, "appeal_id": 0, "city": "", "short_id": 333074775, "online_status": 1, "platform_source": 1, "id": "6629658254756544516", "recommend": false, "lowest_price": 1000, "price": 6000, "author_type": 2, "province": "\u5e7f\u4e1c\u7701", "tags": "[\"\u641e\u7b11\",\"\u521b\u610f\",\"\u751f\u6d3b\",\"\u5267\u60c5\",\"\u5a31\u4e50\"]", "next_month_long_video_price": 9000, "next_month_price": 6000, "is_online": true, "has_phone": true, "core_user_id": 58620442475, "task_status": 1, "protocol_id": 2018008, "nick_name": "\u6881\u731b\u548c\u5c0f\u6b6a", "gender": 1, "aweme_tags": [], "order_cnt": 2, "rate": 1.05, "modify_time": 1558451450, "avatar_uri": "https://p3-dy.byteimg.com/aweme/1080x1080/20ba600013c74b0e5f421.jpeg", "price_info": [{"field": "price", "price": 6000, "video_type": 1, "desc": "1-20s\u89c6\u9891"}, {"field": "long_video_price", "price": 9000, "video_type": 2, "desc": "21-60s\u89c6\u9891"}], "category_id": 5, "unique_id": "liangm11"}, {"long_video_price": 1600, "is_star": true, "rank": 6, "follower": 491681, "create_time": 1554886382, "total_favour_cnt": 4361579, "avg_play": 4640687, "abandon_sign_result": 0, "cut_rate": 0.0, "appeal_id": 0, "city": "\u91cd\u5e86\u5e02", "short_id": 1096496293, "online_status": 1, "platform_source": 1, "id": "6678186162428837900", "recommend": false, "lowest_price": 3000, "price": 1100, "author_type": 1, "province": "", "tags": "[]", "next_month_long_video_price": 1600, "next_month_price": 1100, "is_online": true, "has_phone": true, "core_user_id": 100792859311, "task_status": 1, "protocol_id": 2018006, "nick_name": "\u660e\u667a\u7684\u9009\u62e9", "gender": 2, "aweme_tags": [], "order_cnt": 0, "rate": 1.05, "modify_time": 1558450855, "avatar_uri": "https://p3-dy.byteimg.com/aweme/1080x1080/fdba0000784ffa425539.jpeg", "price_info": [{"field": "price", "price": 1100, "video_type": 1, "desc": "1-20s\u89c6\u9891"}, {"field": "long_video_price", "price": 1600, "video_type": 2, "desc": "21-60s\u89c6\u9891"}], "category_id": 1, "unique_id": 1096496293}, {"long_video_price": 9800, "is_star": true, "rank": 7, "follower": 948797, "create_time": 1543587372, "total_favour_cnt": 6217959, "avg_play": 52314, "abandon_sign_result": 0, "cut_rate": 0.0, "appeal_id": 0, "city": "", "short_id": 568473179, "online_status": 1, "platform_source": 1, "id": "6629657279304040451", "recommend": false, "lowest_price": 1000, "price": 7800, "author_type": 1, "province": null, "tags": "[]", "next_month_long_video_price": 0, "next_month_price": 8100, "is_online": true, "has_phone": true, "core_user_id": 74621556965, "task_status": 1, "protocol_id": 2018006, "nick_name": "\u7eff\u5c0f\u6797\u5b50", "gender": 2, "aweme_tags": [], "order_cnt": 2, "rate": 1.05, "modify_time": 1558451319, "avatar_uri": "https://p3-dy.byteimg.com/aweme/1080x1080/18acf00021cb87f58a960.jpeg", "price_info": [{"field": "price", "price": 7800, "video_type": 1, "desc": "1-20s\u89c6\u9891"}, {"field": "long_video_price", "price": 9800, "video_type": 2, "desc": "21-60s\u89c6\u9891"}], "category_id": 1, "unique_id": "KlmmLzzz"}, {"long_video_price": 9000, "is_star": true, "rank": 8, "follower": 1363880, "create_time": 1535908888, "total_favour_cnt": 7234545, "avg_play": 823511, "abandon_sign_result": 0, "cut_rate": 0.0, "appeal_id": 0, "city": "", "short_id": 588757630, "online_status": 1, "platform_source": 1, "id": "6596678443679612941", "recommend": false, "lowest_price": 2010, "price": 6000, "author_type": 2, "province": "\u8fbd\u5b81\u7701", "tags": "[\"\u97f3\u4e50\",\"\u60c5\u611f\",\"\u827a\u672f\",\"\u751f\u6d3b\",\"\u5a31\u4e50\"]", "next_month_long_video_price": 9000, "next_month_price": 6000, "is_online": true, "has_phone": false, "core_user_id": 95027495774, "task_status": 1, "protocol_id": 2018008, "nick_name": "\u6000\u65e7\u5bb6", "gender": 1, "aweme_tags": [], "order_cnt": 0, "rate": 1.05, "modify_time": 1558451154, "avatar_uri": "https://p3-dy.byteimg.com/aweme/1080x1080/836e001d317091034b43.jpeg", "price_info": [{"field": "price", "price": 6000, "video_type": 1, "desc": "1-20s\u89c6\u9891"}, {"field": "long_video_price", "price": 9000, "video_type": 2, "desc": "21-60s\u89c6\u9891"}], "category_id": 4, "unique_id": 588757630}, {"long_video_price": 94500, "is_star": true, "rank": 9, "follower": 5516906, "create_time": 1535908925, "total_favour_cnt": 40654755, "avg_play": 2842936, "abandon_sign_result": 0, "cut_rate": 0.0, "appeal_id": 0, "city": "\u957f\u6c99", "short_id": 593808001, "online_status": 1, "platform_source": 1, "id": "6596678603465818119", "recommend": false, "lowest_price": 26000, "price": 78750, "author_type": 2, "province": "\u6e56\u5357\u7701", "tags": "[\"\u6bcd\u5a74\",\"\u751f\u6d3b\",\"\u65f6\u5c1a\",\"\u65c5\u884c\",\"\u7f8e\u5986\"]", "next_month_long_video_price": 94500, "next_month_price": 78750, "is_online": true, "has_phone": true, "core_user_id": 95436620600, "task_status": 1, "protocol_id": 2018008, "nick_name": "\u8fa3\u5988\u827e\u5c0f\u946b", "gender": 2, "aweme_tags": [], "order_cnt": 19, "rate": 1.05, "modify_time": 1558451157, "avatar_uri": "https://p9-dy.byteimg.com/aweme/1080x1080/dbcf00065da4f7d111d6.jpeg", "price_info": [{"field": "price", "price": 78750, "video_type": 1, "desc": "1-20s\u89c6\u9891"}, {"field": "long_video_price", "price": 94500, "video_type": 2, "desc": "21-60s\u89c6\u9891"}], "category_id": 4, "unique_id": 593808001}, {"long_video_price": 13000, "is_star": true, "rank": 10, "follower": 828669, "create_time": 1535909034, "total_favour_cnt": 7029884, "avg_play": 762766, "abandon_sign_result": 0, "cut_rate": 0.0, "appeal_id": 0, "city": "", "short_id": 7960937, "online_status": 1, "platform_source": 1, "id": "6596679072657440782", "recommend": true, "lowest_price": 3662, "price": 10000, "author_type": 1, "province": "\u8d35\u5dde\u7701", "tags": "[\"\u821e\u8e48\"]", "next_month_long_video_price": 13000, "next_month_price": 10000, "is_online": true, "has_phone": true, "core_user_id": 58987538286, "task_status": 1, "protocol_id": 2018006, "nick_name": "\u8857\u821e\u6559\u5b66BBOY\u9976\u7fd4", "gender": 1, "aweme_tags": ["\u5e73\u53f0\u63a8\u8350"], "order_cnt": 4, "rate": 1.05, "modify_time": 1558451166, "avatar_uri": "https://p3-dy.byteimg.com/aweme/1080x1080/1730f0001811447e913d3.jpeg", "price_info": [{"field": "price", "price": 10000, "video_type": 1, "desc": "1-20s\u89c6\u9891"}, {"field": "long_video_price", "price": 13000, "video_type": 2, "desc": "21-60s\u89c6\u9891"}], "category_id": 1, "unique_id": "RAOXIANG"}, {"long_video_price": 150000, "is_star": true, "rank": 11, "follower": 10048914, "create_time": 1543602513, "total_favour_cnt": 103706357, "avg_play": 2258460, "abandon_sign_result": 0, "cut_rate": 0.0, "appeal_id": 0, "city": "\u6c88\u9633", "short_id": 987788677, "online_status": 1, "platform_source": 1, "id": "6629722313967271943", "recommend": false, "lowest_price": 34050, "price": 120000, "author_type": 2, "province": "\u8fbd\u5b81\u7701", "tags": "[\"\u4e8c\u6b21\u5143\",\"\u641e\u7b11\",\"\u60c5\u611f\",\"\u5a31\u4e50\",\"\u5267\u60c5\"]", "next_month_long_video_price": 150000, "next_month_price": 120000, "is_online": true, "has_phone": false, "core_user_id": 99247509232, "task_status": 1, "protocol_id": 2018008, "nick_name": "\u55b5\u5c0f\u5154\u6f2b\u753b\uff08\u753b\u5e08\u4e03\u4e03\uff09", "gender": 2, "aweme_tags": [], "order_cnt": 0, "rate": 1.05, "modify_time": 1558452858, "avatar_uri": "https://p1-dy.byteimg.com/aweme/1080x1080/fcc300047a37a5a4f4a1.jpeg", "price_info": [{"field": "price", "price": 120000, "video_type": 1, "desc": "1-20s\u89c6\u9891"}, {"field": "long_video_price", "price": 150000, "video_type": 2, "desc": "21-60s\u89c6\u9891"}], "category_id": 5, "unique_id": "miaoxiaotu"}, {"long_video_price": 24750, "is_star": true, "rank": 12, "follower": 1975566, "create_time": 1543587483, "total_favour_cnt": 19060839, "avg_play": 153875, "abandon_sign_result": 0, "cut_rate": 0.0, "appeal_id": 0, "city": "", "short_id": 4216733, "online_status": 1, "platform_source": 1, "id": "6629657757077209095", "recommend": false, "lowest_price": 2010, "price": 20000, "author_type": 2, "province": null, "tags": "[]", "next_month_long_video_price": 24750, "next_month_price": 20000, "is_online": true, "has_phone": true, "core_user_id": 51306001651, "task_status": 1, "protocol_id": 2018008, "nick_name": "\u7b2c\u4e94\u4eba\u683c\u6696\u6b4c", "gender": 1, "aweme_tags": [], "order_cnt": 1, "rate": 1.05, "modify_time": 1558451380, "avatar_uri": "https://p9-dy.byteimg.com/aweme/1080x1080/1733d000133c21535ae62.jpeg", "price_info": [{"field": "price", "price": 20000, "video_type": 1, "desc": "1-20s\u89c6\u9891"}, {"field": "long_video_price", "price": 24750, "video_type": 2, "desc": "21-60s\u89c6\u9891"}], "category_id": 5, "unique_id": 4216733}, {"long_video_price": 15000, "is_star": true, "rank": 13, "follower": 894532, "create_time": 1540969118, "total_favour_cnt": 8460516, "avg_play": 368625, "abandon_sign_result": 0, "cut_rate": 0.0, "appeal_id": 0, "city": "", "short_id": 166473802, "online_status": 1, "platform_source": 1, "id": "6618411966132125699", "recommend": false, "lowest_price": 1522, "price": 10000, "author_type": 2, "province": "\u6c5f\u82cf\u7701", "tags": "[\"\u7f8e\u98df\"]", "next_month_long_video_price": 15000, "next_month_price": 10000, "is_online": true, "has_phone": true, "core_user_id": 62465917424, "task_status": 1, "protocol_id": 2018008, "nick_name": "\u5c11\u5973\u98df\u5357\u4eac", "gender": 2, "aweme_tags": [], "order_cnt": 1, "rate": 1.05, "modify_time": 1558451205, "avatar_uri": "https://p9-dy.byteimg.com/aweme/1080x1080/90f50006b5b1c3508953.jpeg", "price_info": [{"field": "price", "price": 10000, "video_type": 1, "desc": "1-20s\u89c6\u9891"}, {"field": "long_video_price", "price": 15000, "video_type": 2, "desc": "21-60s\u89c6\u9891"}], "category_id": 5, "unique_id": 166473802}, {"long_video_price": 18000, "is_star": true, "rank": 14, "follower": 944316, "create_time": 1550484533, "total_favour_cnt": 5572949, "avg_play": 589910, "abandon_sign_result": 0, "cut_rate": 0.0, "appeal_id": 0, "city": "\u54c8\u5c14\u6ee8", "short_id": 196078557, "online_status": 1, "platform_source": 1, "id": "6659280364306956299", "recommend": false, "lowest_price": 1611, "price": 12000, "author_type": 1, "province": "\u9ed1\u9f99\u6c5f\u7701", "tags": "[\"\u840c\u5a03\",\"\u751f\u6d3b\",\"\u641e\u7b11\",\"\u6bcd\u5a74\",\"\u521b\u610f\"]", "next_month_long_video_price": 0, "next_month_price": 20000, "is_online": true, "has_phone": true, "core_user_id": 85554811934, "task_status": 1, "protocol_id": 2018006, "nick_name": "\u7a00\u5947\u59d0\u59b9", "gender": 2, "aweme_tags": [], "order_cnt": 8, "rate": 1.05, "modify_time": 1558453143, "avatar_uri": "https://p3-dy.byteimg.com/aweme/1080x1080/1e176000419530f9f158d.jpeg", "price_info": [{"field": "price", "price": 12000, "video_type": 1, "desc": "1-20s\u89c6\u9891"}, {"field": "long_video_price", "price": 18000, "video_type": 2, "desc": "21-60s\u89c6\u9891"}], "category_id": 1, "unique_id": "sisters"}, {"long_video_price": 46666, "is_star": true, "rank": 15, "follower": 1222768, "create_time": 1543603150, "total_favour_cnt": 8348618, "avg_play": 2112468, "abandon_sign_result": 0, "cut_rate": 0.0, "appeal_id": 0, "city": "", "short_id": 5306996, "online_status": 1, "platform_source": 1, "id": "6629725048229855240", "recommend": false, "lowest_price": 11451, "price": 36666, "author_type": 1, "province": null, "tags": "[]", "next_month_long_video_price": 46666, "next_month_price": 36666, "is_online": true, "has_phone": true, "core_user_id": 58515493744, "task_status": 1, "protocol_id": 2018006, "nick_name": "\u5728\u91ceJYR", "gender": 0, "aweme_tags": [], "order_cnt": 0, "rate": 1.05, "modify_time": 1558453001, "avatar_uri": "https://p3-dy.byteimg.com/aweme/1080x1080/46b60008cadae9b65b4b.jpeg", "price_info": [{"field": "price", "price": 36666, "video_type": 1, "desc": "1-20s\u89c6\u9891"}, {"field": "long_video_price", "price": 46666, "video_type": 2, "desc": "21-60s\u89c6\u9891"}], "category_id": 1, "unique_id": 5306996}, {"long_video_price": 45000, "is_star": true, "rank": 16, "follower": 1520193, "create_time": 1543602808, "total_favour_cnt": 22134557, "avg_play": 2691454, "abandon_sign_result": 0, "cut_rate": 0.0, "appeal_id": 0, "city": "", "short_id": 1354012791, "online_status": 1, "platform_source": 1, "id": "6629723575005741060", "recommend": false, "lowest_price": 2010, "price": 30000, "author_type": 2, "province": "\u798f\u5efa\u7701", "tags": "[\"\u624d\u827a\",\"\u641e\u7b11\",\"\u521b\u610f\",\"\u821e\u8e48\"]", "next_month_long_video_price": 0, "next_month_price": 26000, "is_online": true, "has_phone": true, "core_user_id": 103620933565, "task_status": 1, "protocol_id": 2018008, "nick_name": "\u4e8c\u54c8\u718a", "gender": 1, "aweme_tags": [], "order_cnt": 0, "rate": 1.05, "modify_time": 1558452914, "avatar_uri": "https://p3-dy.byteimg.com/aweme/1080x1080/18c5200050ae4cf0f6210.jpeg", "price_info": [{"field": "price", "price": 30000, "video_type": 1, "desc": "1-20s\u89c6\u9891"}, {"field": "long_video_price", "price": 45000, "video_type": 2, "desc": "21-60s\u89c6\u9891"}], "category_id": 5, "unique_id": 1354012791}, {"long_video_price": 1500, "is_star": true, "rank": 17, "follower": 2195676, "create_time": 1543589605, "total_favour_cnt": 17883270, "avg_play": 171691, "abandon_sign_result": 0, "cut_rate": 0.0, "appeal_id": 0, "city": "", "short_id": 12021289, "online_status": 1, "platform_source": 1, "id": "6629666870167339016", "recommend": false, "lowest_price": 2010, "price": 1000, "author_type": 1, "province": "\u6d59\u6c5f\u7701", "tags": "[\"\u7f8e\u5986\"]", "next_month_long_video_price": 1500, "next_month_price": 1000, "is_online": true, "has_phone": true, "core_user_id": 59726722231, "task_status": 1, "protocol_id": 2018006, "nick_name": "\u777f\u5915\u5973\u88c5", "gender": 2, "aweme_tags": [], "order_cnt": 0, "rate": 1.05, "modify_time": 1558452788, "avatar_uri": "https://p1-dy.byteimg.com/aweme/1080x1080/f78e0009d27f75a57d7d.jpeg", "price_info": [{"field": "price", "price": 1000, "video_type": 1, "desc": "1-20s\u89c6\u9891"}, {"field": "long_video_price", "price": 1500, "video_type": 2, "desc": "21-60s\u89c6\u9891"}], "category_id": 1, "unique_id": 12021289}, {"long_video_price": 6000, "is_star": true, "rank": 18, "follower": 1361802, "create_time": 1554088592, "total_favour_cnt": 14076312, "avg_play": 2512969, "abandon_sign_result": 0, "cut_rate": 0.0, "appeal_id": 0, "city": "", "short_id": 969505501, "online_status": 1, "platform_source": 1, "id": "6674759677336616968", "recommend": false, "lowest_price": 2010, "price": 3000, "author_type": 1, "province": "", "tags": "[]", "next_month_long_video_price": 6000, "next_month_price": 3000, "is_online": true, "has_phone": true, "core_user_id": 98936316248, "task_status": 1, "protocol_id": 2018006, "nick_name": "\u7eff\u6bdb\u963f\u59e8", "gender": 2, "aweme_tags": [], "order_cnt": 0, "rate": 1.05, "modify_time": 1558453367, "avatar_uri": "https://p1-dy.byteimg.com/aweme/1080x1080/18a7b000167619ea2688c.jpeg", "price_info": [{"field": "price", "price": 3000, "video_type": 1, "desc": "1-20s\u89c6\u9891"}, {"field": "long_video_price", "price": 6000, "video_type": 2, "desc": "21-60s\u89c6\u9891"}], "category_id": 1, "unique_id": "lvmaoayi"}, {"long_video_price": 8000, "is_star": true, "rank": 19, "follower": 864020, "create_time": 1558057550, "total_favour_cnt": 2715506, "avg_play": 2978347, "abandon_sign_result": 0, "cut_rate": 0.0, "appeal_id": 0, "city": "", "short_id": 852788655, "online_status": 1, "platform_source": 1, "id": "6691806222301003784", "recommend": false, "lowest_price": 6000, "price": 7500, "author_type": 1, "province": "", "tags": "[]", "next_month_long_video_price": 8000, "next_month_price": 7500, "is_online": true, "has_phone": true, "core_user_id": 97259499971, "task_status": 1, "protocol_id": 2018006, "nick_name": "\u8096\u7476_", "gender": 2, "aweme_tags": [], "order_cnt": 0, "rate": 1.05, "modify_time": 1558450456, "avatar_uri": "https://p3-dy.byteimg.com/aweme/1080x1080/1c9e0000519289885b944.jpeg", "price_info": [{"field": "price", "price": 7500, "video_type": 1, "desc": "1-20s\u89c6\u9891"}, {"field": "long_video_price", "price": 8000, "video_type": 2, "desc": "21-60s\u89c6\u9891"}], "category_id": 1, "unique_id": "xyde"}, {"long_video_price": 4500, "is_star": true, "rank": 20, "follower": 531093, "create_time": 1545795772, "total_favour_cnt": 3091140, "avg_play": 155290, "abandon_sign_result": 0, "cut_rate": 0.0, "appeal_id": 0, "city": "", "short_id": 1176424734, "online_status": 1, "platform_source": 1, "id": "6639142290310823949", "recommend": false, "lowest_price": 1000, "price": 3000, "author_type": 2, "province": "\u4e0a\u6d77\u5e02", "tags": "[\"\u65f6\u5c1a\",\"\u751f\u6d3b\",\"\u7f8e\u98df\",\"\u7f8e\u5973\",\"\u521b\u610f\"]", "next_month_long_video_price": 4500, "next_month_price": 3000, "is_online": true, "has_phone": true, "core_user_id": 101512727561, "task_status": 1, "protocol_id": 2018008, "nick_name": "\u4e0a\u6d77\u7f8e\u98df\u653b\u7565", "gender": 2, "aweme_tags": [], "order_cnt": 1, "rate": 1.05, "modify_time": 1558453084, "avatar_uri": "https://p3-dy.byteimg.com/aweme/1080x1080/1b46d0005934a4cbe8949.jpeg", "price_info": [{"field": "price", "price": 3000, "video_type": 1, "desc": "1-20s\u89c6\u9891"}, {"field": "long_video_price", "price": 4500, "video_type": 2, "desc": "21-60s\u89c6\u9891"}], "category_id": 4, "unique_id": "shmsgl310"}]}}